README
setup.py
magpielib/__init__.py
magpielib/application.py
magpielib/parse.py
magpielib/service_map.py
magpielib.egg-info/PKG-INFO
magpielib.egg-info/SOURCES.txt
magpielib.egg-info/dependency_links.txt
magpielib.egg-info/requires.txt
magpielib.egg-info/top_level.txt
magpielib/handler/__init__.py
magpielib/handler/handler_util.py
magpielib/handler/patchhandler.py
magpielib/handler/reqhandler.py
magpielib/handler/testhandelr.py
magpielib/handler/wshandler.py
magpielib/util/__init__.py
magpielib/util/alembic.py
magpielib/util/api_models.py
magpielib/util/asynredis.py
magpielib/util/db.py
magpielib/util/doc.py
magpielib/util/helper.py
magpielib/util/log.py
magpielib/util/pcore.py
magpielib/util/pcoresync.py
magpielib/util/pcorewait.py
magpielib/util/pcorews.py
magpielib/util/reds.py
magpielib/util/table_query.py