Metadata-Version: 2.1
Name: magpielib
Version: 1.4.0
Summary: magpie struct dependence
Home-page: UNKNOWN
Author: zhongyi
Author-email: conghoulin@163.com
License: UNKNOWN
Platform: UNKNOWN
Classifier: Programming Language :: Python :: 3
Classifier: License :: OSI Approved :: MIT License
Classifier: Operating System :: OS Independent
Requires-Python: >=3.7
